socolors/__init__.py
socolors/styles_discovery.py
socolors/styles/notebook.mplstyle
socolors/styles/sobase.mplstyle
socolors/styles/journals/apj-fullwidth.mplstyle
socolors/styles/journals/apj.mplstyle
socolors/styles/journals/jcap-fullwidth.mplstyle
socolors/styles/journals/jcap.mplstyle
socolors/styles/journals/mnras-fullwidth.mplstyle
socolors/styles/journals/mnras.mplstyle
socolors-0.0.2.dist-info/licenses/LICENSE
socolors-0.0.2.dist-info/METADATA
socolors-0.0.2.dist-info/WHEEL
socolors-0.0.2.dist-info/top_level.txt
socolors-0.0.2.dist-info/RECORD
