Metadata-Version: 2.4
Name: socolors
Version: 0.0.2
Requires-Python: >=3.11
License-File: LICENSE
Requires-Dist: matplotlib
Provides-Extra: dev
Requires-Dist: ruff==0.14.5; extra == "dev"
Requires-Dist: pre-commit; extra == "dev"
Dynamic: license-file
